README.md
setup.cfg
setup.py
ie_mbdbl2018_tsaliba/__init__.py
ie_mbdbl2018_tsaliba/myfirstfunc.py
ie_mbdbl2018_tsaliba.egg-info/PKG-INFO
ie_mbdbl2018_tsaliba.egg-info/SOURCES.txt
ie_mbdbl2018_tsaliba.egg-info/dependency_links.txt
ie_mbdbl2018_tsaliba.egg-info/not-zip-safe
ie_mbdbl2018_tsaliba.egg-info/top_level.txt