Metadata-Version: 1.0
Name: ie-mbdbl2018-tsaliba
Version: 0.1
Summary: Python Packaging Starting Kit - Simple Structure to creater your own package - for training purposes!
Home-page: https://github.com/Salibt/ie_mbdbl2018_tsaliba
Author: Tarek Saliba
Author-email: tarek.saliba@student.ie.edu
License: MIT
Platform: UNKNOWN
